[
  [
    {
      "processed_boxes": [
        {
          "order_number": "1692",
          "symbol": "IDE CR J-CH",
          "quantity": 2000,
          "output": 2,
          "hierarchy": "priority",
          "total_weight": 184,
          "part": 1,
          "remaining": 0,
          "arapack_lot": "25281"
        },
        {
          "authorized_refile": false
        }
      ],
      "sheet": "67ddbee6a331fd508605b12d",
      "scheduled_date": "2025-03-27",
      "start_time": "08:20",
      "end_time": "08:47",
      "refile": 7.2,
      "grams_per_m2": 354,
      "linear_meters": 1578,
      "speed": 60
    },
    {
      "processed_boxes": [
        {
          "order_number": "3023775",
          "symbol": "SEPARADOR 5",
          "quantity": 30000,
          "output": 4,
          "hierarchy": "priority",
          "total_weight": 2654,
          "part": 1,
          "remaining": 0,
          "arapack_lot": "25318"
        },
        {
          "authorized_refile": false
        }
      ],
      "sheet": "67ddbee6a331fd508605b134",
      "scheduled_date": "2025-03-27",
      "start_time": "08:47",
      "end_time": "11:20",
      "refile": 4,
      "grams_per_m2": 350,
      "linear_meters": 9075,
      "speed": 60
    },
    {
      "processed_boxes": [
        {
          "order_number": "120257111659",
          "symbol": "GTP SEP RAYADO 88X36",
          "quantity": 1500,
          "output": 1,
          "hierarchy": "priority",
          "total_weight": 337,
          "part": 1,
          "remaining": 0,
          "arapack_lot": "25284"
        },
        {
          "order_number": "3023741",
          "symbol": "SEPARADOR 1",
          "quantity": 983,
          "output": 1,
          "hierarchy": "complement",
          "total_weight": 76,
          "part": 1,
          "remaining": 2817,
          "arapack_lot": "25295"
        },
        {
          "authorized_refile": false
        }
      ],
      "sheet": "67ddbee6a331fd508605b13d",
      "scheduled_date": "2025-03-27",
      "start_time": "11:20",
      "end_time": "11:40",
      "refile": 4.0,
      "grams_per_m2": 345,
      "linear_meters": 1110,
      "speed": 60
    },
    {
      "processed_boxes": [
        {
          "order_number": "3023741",
          "symbol": "SEPARADOR 1",
          "quantity": 2817,
          "output": 4,
          "hierarchy": "priority",
          "total_weight": 219,
          "part": 2,
          "remaining": 0,
          "arapack_lot": "25295"
        },
        {
          "authorized_refile": true
        }
      ],
      "sheet": "67ddbee6a331fd508605b130",
      "scheduled_date": "2025-03-27",
      "start_time": "11:40",
      "end_time": "12:35",
      "refile": 14,
      "grams_per_m2": 345,
      "linear_meters": 3183,
      "speed": 60
    }
  ],
  {
    "output_sample": [
      {
        "processed_boxes": [
          {
            "order_number": "4500249553",
            "symbol": "DEG NO. 228",
            "quantity": 3213,
            "output": 1,
            "hierarchy": "complement",
            "part": 1,
            "remaining": 1787,
            "arapack_lot": "25281"
          },
          {
            "order_number": "4500249553",
            "symbol": "DEG NO. 229",
            "quantity": 3000,
            "output": 1,
            "hierarchy": "priority",
            "part": 1,
            "remaining": 0,
            "arapack_lot": "25282"
          },
          {
            "authorized_refile": false
          }
        ],
        "sheet": "67ddbee6a331fd508605b13d",
        "scheduled_date": "2025-02-23",
        "start_time": "08:20",
        "end_time": "9:35",
        "refile": 7.0,
        "grams_per_m2": 345,
        "total_weight": 41.595,
        "linear_meters": 4530,
        "speed": 60
      },
      {
        "processed_boxes": [
          {
            "order_number": "4500249555",
            "symbol": "DEG CR SWABS 500CT C24",
            "quantity": 4000,
            "output": 1,
            "hierarchy": "priority",
            "part": 1,
            "remaining": 0,
            "arapack_lot": "25283",
            "linear_meters": 6588,
            "total_weight": 
          },
          {
            "order_number": "4500249555",
            "symbol": "DEG CR SWABS 375CT C24",
            "quantity": 2500,
            "output": 1,
            "hierarchy": "complement",
            "part": 1,
            "remaining": 0,
            "arapack_lot": "25284"
          },
          {
            "authorized_refile": false
          }
        ],
        "sheet": "67ddbee6a331fd508605b13d",
        "scheduled_date": "2025-02-23",
        "start_time": "08:20",
        "end_time": "22:30",
        "refile": 6.0,
        "grams_per_m2": 354,
        "speed": 60
      },
      {
        "processed_boxes": [
          {
            "order_number": "4500249556",
            "symbol": "DEG CR SWABS 500CT C24",
            "quantity": 5000,
            "output": 1,
            "hierarchy": "priority"
          },
          {
            "authorized_refile": true
          }
        ],
        "sheet": "67ddbee6a331fd508605b12d",
        "scheduled_date": "2025-02-26",
        "start_time": "08:20",
        "end_time": "22:30",
        "refile": 17.9,
        "grams_per_m2": 354,
        "linear_meters": 137.25,
        "total_weight": 48.5865,
        "speed": 60
      },
      {
        "processed_boxes": [
          {
            "order_number": "4500249554",
            "symbol": "DEG CR PRUDENCE",
            "quantity": 2000,
            "output": 1,
            "hierarchy": "priority"
          },
          {
            "authorized_refile": true
          }
        ],
        "sheet": "67ddbee6a331fd508605b12f",
        "scheduled_date": "2025-02-26",
        "start_time": "08:20",
        "end_time": "22:30",
        "refile": 17.8,
        "grams_per_m2": 390,
        "linear_meters": 19.16,
        "total_weight": 7.4724,
        "speed": 60
      }
    ]
  }
]